{"data":{"site":{"siteMetadata":{"siteTitle":"DaniJG personal site","siteDescription":"Daniel Jimenez Garcia personal site","siteImage":"/banner.png","siteUrl":"https://danijg.github.io","pathPrefix":"/","siteLanguage":"en","ogLanguage":"en_US","author":"Daniel Jimenez Garcia","authorDescription":"Welcome! I am a SW developer who loves to code and finding simple elegant solutions to problems. At work, these are mostly organizational and people problems. In my free time I like to write articles, tutorials or simply experiment with some code!","avatar":"/avatar.jpg","avatarAltText":"Daniel Jimenez Garcia","twitterSite":"","twitterCreator":"https://twitter.com/Dani_djg","uiText":{"feedShowMoreButton":"show more","feedSearchPlaceholder":"search","cardReadMoreButton":"read more →","allTagsButton":"all tags"},"feedItems":{"limit":50,"yearSeparator":false,"yearSeparatorSkipFirst":true,"contentTypes":{"links":{"beforeTitle":"🔗 "}}},"feedSearch":{"symbol":"🔍"},"social":[{"icon":"twitter","url":"https://twitter.com/Dani_djg","altText":"Twitter profile"},{"icon":"github","url":"https://github.com/DaniJG","altText":"GitHub contributions and projects"},{"icon":"stack-overflow","url":"https://stackoverflow.com/users/1836935/daniel-j-g","altText":"Stack Overflow profile"},{"icon":"leanpub","url":"https://www.dotnetcurry.com/author/daniel-jimenez-garcia","altText":"Articles on DotNetCurry"},{"icon":"pied-piper-alt","url":"https://kaizendorks.github.io","altText":"KaizenDorks contributor"},{"icon":"linkedin","url":"https://www.linkedin.com/in/daniel-jg/","altText":"LinkedIn profile"},{"icon":"node-js","url":"https://www.npmjs.com/~danijg","altText":"NPM packages"}]}}}}